torch_secorder/__init__.py
torch_secorder/_version.py
torch_secorder/analysis/__init__.py
torch_secorder/analysis/eigensolvers.py
torch_secorder/analysis/landscape.py
torch_secorder/approximations/__init__.py
torch_secorder/approximations/fisher_diagonal.py
torch_secorder/approximations/fisher_trace.py
torch_secorder/approximations/gauss_newton.py
torch_secorder/core/__init__.py
torch_secorder/core/gvp.py
torch_secorder/core/hessian_diagonal.py
torch_secorder/core/hessian_trace.py
torch_secorder/core/hvp.py
torch_secorder/core/per_layer_curvature.py
torch_secorder/core/utils.py
torch_secorder-0.0.1.dist-info/LICENSE
torch_secorder-0.0.1.dist-info/METADATA
torch_secorder-0.0.1.dist-info/WHEEL
torch_secorder-0.0.1.dist-info/RECORD
