Metadata-Version: 2.3
Name: torch-secorder
Version: 0.0.1
Summary: A PyTorch library for second-order optimization and analysis
Author: PyBrainn
Author-email: pybrainn@heyshinde.com
Requires-Python: >=3.11
Classifier: Programming Language :: Python :: 3
Classifier: Programming Language :: Python :: 3.11
Classifier: Programming Language :: Python :: 3.12
Classifier: Programming Language :: Python :: 3.13
Requires-Dist: numpy (>=2.3.0,<3.0)
Requires-Dist: torch (>=2.7.1,<3.0)
